{"nodes": [{"id": "c_users_lifecycle_desktop_gptvli_event_handlers_py", "label": "event_handlers.py", "file_type": "code", "source_file": "event_handlers.py", "source_location": "L1"}, {"id": "gptvli_event_handlers_eventhandlers", "label": "EventHandlers", "file_type": "code", "source_file": "event_handlers.py", "source_location": "L12"}, {"id": "gptvli_event_handlers_eventhandlers_init", "label": ".__init__()", "file_type": "code", "source_file": "event_handlers.py", "source_location": "L18"}, {"id": "gptvli_event_handlers_eventhandlers_register_handlers", "label": ".register_handlers()", "file_type": "code", "source_file": "event_handlers.py", "source_location": "L22"}, {"id": "gptvli_event_handlers_eventhandlers_enqueue_rematch", "label": "._enqueue_rematch()", "file_type": "code", "source_file": "event_handlers.py", "source_location": "L40"}, {"id": "gptvli_event_handlers_eventhandlers_enqueue_environment_variable_task", "label": "._enqueue_environment_variable_task()", "file_type": "code", "source_file": "event_handlers.py", "source_location": "L67"}, {"id": "gptvli_event_handlers_eventhandlers_dispatch_environment_variable_task", "label": "._dispatch_environment_variable_task()", "file_type": "code", "source_file": "event_handlers.py", "source_location": "L81"}, {"id": "gptvli_event_handlers_eventhandlers_dispatch_vector_sync_task", "label": "._dispatch_vector_sync_task()", "file_type": "code", "source_file": "event_handlers.py", "source_location": "L94"}, {"id": "gptvli_event_handlers_eventhandlers_enqueue_vector_sync_task", "label": "._enqueue_vector_sync_task()", "file_type": "code", "source_file": "event_handlers.py", "source_location": "L107"}, {"id": "property", "label": "Property", "file_type": "code", "source_file": "event_handlers.py", "source_location": "L107"}, {"id": "gptvli_event_handlers_eventhandlers_on_session_after_commit", "label": "._on_session_after_commit()", "file_type": "code", "source_file": "event_handlers.py", "source_location": "L122"}, {"id": "session", "label": "Session", "file_type": "code", "source_file": "event_handlers.py", "source_location": "L122"}, {"id": "gptvli_event_handlers_eventhandlers_on_session_after_rollback", "label": "._on_session_after_rollback()", "file_type": "code", "source_file": "event_handlers.py", "source_location": "L146"}, {"id": "gptvli_event_handlers_eventhandlers_on_property_created", "label": "._on_property_created()", "file_type": "code", "source_file": "event_handlers.py", "source_location": "L150"}, {"id": "gptvli_event_handlers_eventhandlers_on_property_updated", "label": "._on_property_updated()", "file_type": "code", "source_file": "event_handlers.py", "source_location": "L160"}, {"id": "gptvli_event_handlers_eventhandlers_on_property_deleted", "label": "._on_property_deleted()", "file_type": "code", "source_file": "event_handlers.py", "source_location": "L187"}, {"id": "gptvli_event_handlers_eventhandlers_on_customer_created", "label": "._on_customer_created()", "file_type": "code", "source_file": "event_handlers.py", "source_location": "L193"}, {"id": "customer", "label": "Customer", "file_type": "code", "source_file": "event_handlers.py", "source_location": "L193"}, {"id": "gptvli_event_handlers_eventhandlers_on_customer_updated", "label": "._on_customer_updated()", "file_type": "code", "source_file": "event_handlers.py", "source_location": "L200"}, {"id": "gptvli_event_handlers_eventhandlers_get_property_changes", "label": "._get_property_changes()", "file_type": "code", "source_file": "event_handlers.py", "source_location": "L220"}, {"id": "any", "label": "Any", "file_type": "code", "source_file": "event_handlers.py", "source_location": "L220"}, {"id": "gptvli_event_handlers_eventhandlers_get_customer_changes", "label": "._get_customer_changes()", "file_type": "code", "source_file": "event_handlers.py", "source_location": "L231"}, {"id": "gptvli_event_handlers_eventhandlers_on_environment_variable_created", "label": "._on_environment_variable_created()", "file_type": "code", "source_file": "event_handlers.py", "source_location": "L242"}, {"id": "environmentvariable", "label": "EnvironmentVariable", "file_type": "code", "source_file": "event_handlers.py", "source_location": "L242"}, {"id": "gptvli_event_handlers_eventhandlers_on_environment_variable_updated", "label": "._on_environment_variable_updated()", "file_type": "code", "source_file": "event_handlers.py", "source_location": "L250"}, {"id": "gptvli_event_handlers_eventhandlers_on_environment_variable_deleted", "label": "._on_environment_variable_deleted()", "file_type": "code", "source_file": "event_handlers.py", "source_location": "L263"}, {"id": "gptvli_event_handlers_eventhandlers_get_environment_variable_changes", "label": "._get_environment_variable_changes()", "file_type": "code", "source_file": "event_handlers.py", "source_location": "L271"}, {"id": "gptvli_event_handlers_eventhandlers_manual_trigger_matching", "label": ".manual_trigger_matching()", "file_type": "code", "source_file": "event_handlers.py", "source_location": "L310"}, {"id": "gptvli_event_handlers_eventhandlers_get_matching_stats", "label": ".get_matching_stats()", "file_type": "code", "source_file": "event_handlers.py", "source_location": "L353"}, {"id": "gptvli_event_handlers_rationale_13", "label": "Database event handlers that enqueue lightweight rematch requests.     Heavy ma", "file_type": "rationale", "source_file": "event_handlers.py", "source_location": "L13"}, {"id": "gptvli_event_handlers_rationale_68", "label": "Queue environment variable change tasks to run after DB commit.         Running", "file_type": "rationale", "source_file": "event_handlers.py", "source_location": "L68"}, {"id": "gptvli_event_handlers_rationale_108", "label": "Queue vector sync tasks to run after DB commit.         Running Celery `.delay(", "file_type": "rationale", "source_file": "event_handlers.py", "source_location": "L108"}, {"id": "gptvli_event_handlers_rationale_315", "label": "Manual trigger now enqueues rematch requests for worker processing.", "file_type": "rationale", "source_file": "event_handlers.py", "source_location": "L315"}], "edges": [{"source": "c_users_lifecycle_desktop_gptvli_event_handlers_py", "target": "logging", "relation": "imports", "context": "import", "confidence": "EXTRACTED", "source_file": "event_handlers.py", "source_location": "L1", "weight": 1.0}, {"source": "c_users_lifecycle_desktop_gptvli_event_handlers_py", "target": "datetime", "relation": "imports_from", "context": "import", "confidence": "EXTRACTED", "source_file": "event_handlers.py", "source_location": "L2", "weight": 1.0}, {"source": "c_users_lifecycle_desktop_gptvli_event_handlers_py", "target": "typing", "relation": "imports_from", "context": "import", "confidence": "EXTRACTED", "source_file": "event_handlers.py", "source_location": "L3", "weight": 1.0}, {"source": "c_users_lifecycle_desktop_gptvli_event_handlers_py", "target": "sqlalchemy", "relation": "imports_from", "context": "import", "confidence": "EXTRACTED", "source_file": "event_handlers.py", "source_location": "L5", "weight": 1.0}, {"source": "c_users_lifecycle_desktop_gptvli_event_handlers_py", "target": "sqlalchemy_orm", "relation": "imports_from", "context": "import", "confidence": "EXTRACTED", "source_file": "event_handlers.py", "source_location": "L6", "weight": 1.0}, {"source": "c_users_lifecycle_desktop_gptvli_event_handlers_py", "target": "database", "relation": "imports_from", "context": "import", "confidence": "EXTRACTED", "source_file": "event_handlers.py", "source_location": "L8", "weight": 1.0}, {"source": "c_users_lifecycle_desktop_gptvli_event_handlers_py", "target": "sqlalchemy_models", "relation": "imports_from", "context": "import", "confidence": "EXTRACTED", "source_file": "event_handlers.py", "source_location": "L9", "weight": 1.0}, {"source": "c_users_lifecycle_desktop_gptvli_event_handlers_py", "target": "gptvli_event_handlers_eventhandlers", "relation": "contains", "confidence": "EXTRACTED", "source_file": "event_handlers.py", "source_location": "L12", "weight": 1.0}, {"source": "gptvli_event_handlers_eventhandlers", "target": "gptvli_event_handlers_eventhandlers_init", "relation": "method", "confidence": "EXTRACTED", "source_file": "event_handlers.py", "source_location": "L18", "weight": 1.0}, {"source": "gptvli_event_handlers_eventhandlers", "target": "gptvli_event_handlers_eventhandlers_register_handlers", "relation": "method", "confidence": "EXTRACTED", "source_file": "event_handlers.py", "source_location": "L22", "weight": 1.0}, {"source": "gptvli_event_handlers_eventhandlers", "target": "gptvli_event_handlers_eventhandlers_enqueue_rematch", "relation": "method", "confidence": "EXTRACTED", "source_file": "event_handlers.py", "source_location": "L40", "weight": 1.0}, {"source": "gptvli_event_handlers_eventhandlers", "target": "gptvli_event_handlers_eventhandlers_enqueue_environment_variable_task", "relation": "method", "confidence": "EXTRACTED", "source_file": "event_handlers.py", "source_location": "L67", "weight": 1.0}, {"source": "gptvli_event_handlers_eventhandlers", "target": "gptvli_event_handlers_eventhandlers_dispatch_environment_variable_task", "relation": "method", "confidence": "EXTRACTED", "source_file": "event_handlers.py", "source_location": "L81", "weight": 1.0}, {"source": "gptvli_event_handlers_eventhandlers", "target": "gptvli_event_handlers_eventhandlers_dispatch_vector_sync_task", "relation": "method", "confidence": "EXTRACTED", "source_file": "event_handlers.py", "source_location": "L94", "weight": 1.0}, {"source": "gptvli_event_handlers_eventhandlers", "target": "gptvli_event_handlers_eventhandlers_enqueue_vector_sync_task", "relation": "method", "confidence": "EXTRACTED", "source_file": "event_handlers.py", "source_location": "L107", "weight": 1.0}, {"source": "gptvli_event_handlers_eventhandlers_enqueue_vector_sync_task", "target": "property", "relation": "references", "context": "generic_arg", "confidence": "EXTRACTED", "source_file": "event_handlers.py", "source_location": "L107", "weight": 1.0}, {"source": "gptvli_event_handlers_eventhandlers", "target": "gptvli_event_handlers_eventhandlers_on_session_after_commit", "relation": "method", "confidence": "EXTRACTED", "source_file": "event_handlers.py", "source_location": "L122", "weight": 1.0}, {"source": "gptvli_event_handlers_eventhandlers_on_session_after_commit", "target": "session", "relation": "references", "context": "parameter_type", "confidence": "EXTRACTED", "source_file": "event_handlers.py", "source_location": "L122", "weight": 1.0}, {"source": "gptvli_event_handlers_eventhandlers", "target": "gptvli_event_handlers_eventhandlers_on_session_after_rollback", "relation": "method", "confidence": "EXTRACTED", "source_file": "event_handlers.py", "source_location": "L146", "weight": 1.0}, {"source": "gptvli_event_handlers_eventhandlers_on_session_after_rollback", "target": "session", "relation": "references", "context": "parameter_type", "confidence": "EXTRACTED", "source_file": "event_handlers.py", "source_location": "L146", "weight": 1.0}, {"source": "gptvli_event_handlers_eventhandlers", "target": "gptvli_event_handlers_eventhandlers_on_property_created", "relation": "method", "confidence": "EXTRACTED", "source_file": "event_handlers.py", "source_location": "L150", "weight": 1.0}, {"source": "gptvli_event_handlers_eventhandlers_on_property_created", "target": "property", "relation": "references", "context": "parameter_type", "confidence": "EXTRACTED", "source_file": "event_handlers.py", "source_location": "L150", "weight": 1.0}, {"source": "gptvli_event_handlers_eventhandlers", "target": "gptvli_event_handlers_eventhandlers_on_property_updated", "relation": "method", "confidence": "EXTRACTED", "source_file": "event_handlers.py", "source_location": "L160", "weight": 1.0}, {"source": "gptvli_event_handlers_eventhandlers_on_property_updated", "target": "property", "relation": "references", "context": "parameter_type", "confidence": "EXTRACTED", "source_file": "event_handlers.py", "source_location": "L160", "weight": 1.0}, {"source": "gptvli_event_handlers_eventhandlers", "target": "gptvli_event_handlers_eventhandlers_on_property_deleted", "relation": "method", "confidence": "EXTRACTED", "source_file": "event_handlers.py", "source_location": "L187", "weight": 1.0}, {"source": "gptvli_event_handlers_eventhandlers_on_property_deleted", "target": "property", "relation": "references", "context": "parameter_type", "confidence": "EXTRACTED", "source_file": "event_handlers.py", "source_location": "L187", "weight": 1.0}, {"source": "gptvli_event_handlers_eventhandlers", "target": "gptvli_event_handlers_eventhandlers_on_customer_created", "relation": "method", "confidence": "EXTRACTED", "source_file": "event_handlers.py", "source_location": "L193", "weight": 1.0}, {"source": "gptvli_event_handlers_eventhandlers_on_customer_created", "target": "customer", "relation": "references", "context": "parameter_type", "confidence": "EXTRACTED", "source_file": "event_handlers.py", "source_location": "L193", "weight": 1.0}, {"source": "gptvli_event_handlers_eventhandlers", "target": "gptvli_event_handlers_eventhandlers_on_customer_updated", "relation": "method", "confidence": "EXTRACTED", "source_file": "event_handlers.py", "source_location": "L200", "weight": 1.0}, {"source": "gptvli_event_handlers_eventhandlers_on_customer_updated", "target": "customer", "relation": "references", "context": "parameter_type", "confidence": "EXTRACTED", "source_file": "event_handlers.py", "source_location": "L200", "weight": 1.0}, {"source": "gptvli_event_handlers_eventhandlers", "target": "gptvli_event_handlers_eventhandlers_get_property_changes", "relation": "method", "confidence": "EXTRACTED", "source_file": "event_handlers.py", "source_location": "L220", "weight": 1.0}, {"source": "gptvli_event_handlers_eventhandlers_get_property_changes", "target": "property", "relation": "references", "context": "parameter_type", "confidence": "EXTRACTED", "source_file": "event_handlers.py", "source_location": "L220", "weight": 1.0}, {"source": "gptvli_event_handlers_eventhandlers_get_property_changes", "target": "any", "relation": "references", "context": "generic_arg", "confidence": "EXTRACTED", "source_file": "event_handlers.py", "source_location": "L220", "weight": 1.0}, {"source": "gptvli_event_handlers_eventhandlers", "target": "gptvli_event_handlers_eventhandlers_get_customer_changes", "relation": "method", "confidence": "EXTRACTED", "source_file": "event_handlers.py", "source_location": "L231", "weight": 1.0}, {"source": "gptvli_event_handlers_eventhandlers_get_customer_changes", "target": "customer", "relation": "references", "context": "parameter_type", "confidence": "EXTRACTED", "source_file": "event_handlers.py", "source_location": "L231", "weight": 1.0}, {"source": "gptvli_event_handlers_eventhandlers_get_customer_changes", "target": "any", "relation": "references", "context": "generic_arg", "confidence": "EXTRACTED", "source_file": "event_handlers.py", "source_location": "L231", "weight": 1.0}, {"source": "gptvli_event_handlers_eventhandlers", "target": "gptvli_event_handlers_eventhandlers_on_environment_variable_created", "relation": "method", "confidence": "EXTRACTED", "source_file": "event_handlers.py", "source_location": "L242", "weight": 1.0}, {"source": "gptvli_event_handlers_eventhandlers_on_environment_variable_created", "target": "environmentvariable", "relation": "references", "context": "parameter_type", "confidence": "EXTRACTED", "source_file": "event_handlers.py", "source_location": "L242", "weight": 1.0}, {"source": "gptvli_event_handlers_eventhandlers", "target": "gptvli_event_handlers_eventhandlers_on_environment_variable_updated", "relation": "method", "confidence": "EXTRACTED", "source_file": "event_handlers.py", "source_location": "L250", "weight": 1.0}, {"source": "gptvli_event_handlers_eventhandlers_on_environment_variable_updated", "target": "environmentvariable", "relation": "references", "context": "parameter_type", "confidence": "EXTRACTED", "source_file": "event_handlers.py", "source_location": "L250", "weight": 1.0}, {"source": "gptvli_event_handlers_eventhandlers", "target": "gptvli_event_handlers_eventhandlers_on_environment_variable_deleted", "relation": "method", "confidence": "EXTRACTED", "source_file": "event_handlers.py", "source_location": "L263", "weight": 1.0}, {"source": "gptvli_event_handlers_eventhandlers_on_environment_variable_deleted", "target": "environmentvariable", "relation": "references", "context": "parameter_type", "confidence": "EXTRACTED", "source_file": "event_handlers.py", "source_location": "L263", "weight": 1.0}, {"source": "gptvli_event_handlers_eventhandlers", "target": "gptvli_event_handlers_eventhandlers_get_environment_variable_changes", "relation": "method", "confidence": "EXTRACTED", "source_file": "event_handlers.py", "source_location": "L271", "weight": 1.0}, {"source": "gptvli_event_handlers_eventhandlers_get_environment_variable_changes", "target": "environmentvariable", "relation": "references", "context": "parameter_type", "confidence": "EXTRACTED", "source_file": "event_handlers.py", "source_location": "L271", "weight": 1.0}, {"source": "gptvli_event_handlers_eventhandlers_get_environment_variable_changes", "target": "any", "relation": "references", "context": "generic_arg", "confidence": "EXTRACTED", "source_file": "event_handlers.py", "source_location": "L271", "weight": 1.0}, {"source": "gptvli_event_handlers_eventhandlers", "target": "gptvli_event_handlers_eventhandlers_on_session_after_commit", "relation": "method", "confidence": "EXTRACTED", "source_file": "event_handlers.py", "source_location": "L282", "weight": 1.0}, {"source": "gptvli_event_handlers_eventhandlers_on_session_after_commit", "target": "session", "relation": "references", "context": "parameter_type", "confidence": "EXTRACTED", "source_file": "event_handlers.py", "source_location": "L282", "weight": 1.0}, {"source": "gptvli_event_handlers_eventhandlers", "target": "gptvli_event_handlers_eventhandlers_on_session_after_rollback", "relation": "method", "confidence": "EXTRACTED", "source_file": "event_handlers.py", "source_location": "L306", "weight": 1.0}, {"source": "gptvli_event_handlers_eventhandlers_on_session_after_rollback", "target": "session", "relation": "references", "context": "parameter_type", "confidence": "EXTRACTED", "source_file": "event_handlers.py", "source_location": "L306", "weight": 1.0}, {"source": "gptvli_event_handlers_eventhandlers", "target": "gptvli_event_handlers_eventhandlers_manual_trigger_matching", "relation": "method", "confidence": "EXTRACTED", "source_file": "event_handlers.py", "source_location": "L310", "weight": 1.0}, {"source": "gptvli_event_handlers_eventhandlers", "target": "gptvli_event_handlers_eventhandlers_get_matching_stats", "relation": "method", "confidence": "EXTRACTED", "source_file": "event_handlers.py", "source_location": "L353", "weight": 1.0}, {"source": "gptvli_event_handlers_eventhandlers_get_matching_stats", "target": "any", "relation": "references", "context": "generic_arg", "confidence": "EXTRACTED", "source_file": "event_handlers.py", "source_location": "L353", "weight": 1.0}, {"source": "gptvli_event_handlers_eventhandlers_enqueue_environment_variable_task", "target": "gptvli_event_handlers_eventhandlers_dispatch_environment_variable_task", "relation": "calls", "context": "call", "confidence": "EXTRACTED", "source_file": "event_handlers.py", "source_location": "L79", "weight": 1.0}, {"source": "gptvli_event_handlers_eventhandlers_enqueue_vector_sync_task", "target": "gptvli_event_handlers_eventhandlers_dispatch_vector_sync_task", "relation": "calls", "context": "call", "confidence": "EXTRACTED", "source_file": "event_handlers.py", "source_location": "L120", "weight": 1.0}, {"source": "gptvli_event_handlers_eventhandlers_on_session_after_commit", "target": "gptvli_event_handlers_eventhandlers_dispatch_vector_sync_task", "relation": "calls", "context": "call", "confidence": "EXTRACTED", "source_file": "event_handlers.py", "source_location": "L132", "weight": 1.0}, {"source": "gptvli_event_handlers_eventhandlers_on_session_after_commit", "target": "gptvli_event_handlers_eventhandlers_dispatch_environment_variable_task", "relation": "calls", "context": "call", "confidence": "EXTRACTED", "source_file": "event_handlers.py", "source_location": "L144", "weight": 1.0}, {"source": "gptvli_event_handlers_eventhandlers_on_property_created", "target": "gptvli_event_handlers_eventhandlers_enqueue_rematch", "relation": "calls", "context": "call", "confidence": "EXTRACTED", "source_file": "event_handlers.py", "source_location": "L153", "weight": 1.0}, {"source": "gptvli_event_handlers_eventhandlers_on_property_created", "target": "gptvli_event_handlers_eventhandlers_enqueue_vector_sync_task", "relation": "calls", "context": "call", "confidence": "EXTRACTED", "source_file": "event_handlers.py", "source_location": "L154", "weight": 1.0}, {"source": "gptvli_event_handlers_eventhandlers_on_property_updated", "target": "gptvli_event_handlers_eventhandlers_get_property_changes", "relation": "calls", "context": "call", "confidence": "EXTRACTED", "source_file": "event_handlers.py", "source_location": "L162", "weight": 1.0}, {"source": "gptvli_event_handlers_eventhandlers_on_property_updated", "target": "gptvli_event_handlers_eventhandlers_enqueue_rematch", "relation": "calls", "context": "call", "confidence": "EXTRACTED", "source_file": "event_handlers.py", "source_location": "L180", "weight": 1.0}, {"source": "gptvli_event_handlers_eventhandlers_on_property_updated", "target": "gptvli_event_handlers_eventhandlers_enqueue_vector_sync_task", "relation": "calls", "context": "call", "confidence": "EXTRACTED", "source_file": "event_handlers.py", "source_location": "L181", "weight": 1.0}, {"source": "gptvli_event_handlers_eventhandlers_on_property_deleted", "target": "gptvli_event_handlers_eventhandlers_enqueue_vector_sync_task", "relation": "calls", "context": "call", "confidence": "EXTRACTED", "source_file": "event_handlers.py", "source_location": "L189", "weight": 1.0}, {"source": "gptvli_event_handlers_eventhandlers_on_customer_created", "target": "gptvli_event_handlers_eventhandlers_enqueue_rematch", "relation": "calls", "context": "call", "confidence": "EXTRACTED", "source_file": "event_handlers.py", "source_location": "L196", "weight": 1.0}, {"source": "gptvli_event_handlers_eventhandlers_on_customer_updated", "target": "gptvli_event_handlers_eventhandlers_get_customer_changes", "relation": "calls", "context": "call", "confidence": "EXTRACTED", "source_file": "event_handlers.py", "source_location": "L202", "weight": 1.0}, {"source": "gptvli_event_handlers_eventhandlers_on_customer_updated", "target": "gptvli_event_handlers_eventhandlers_enqueue_rematch", "relation": "calls", "context": "call", "confidence": "EXTRACTED", "source_file": "event_handlers.py", "source_location": "L216", "weight": 1.0}, {"source": "gptvli_event_handlers_eventhandlers_on_environment_variable_created", "target": "gptvli_event_handlers_eventhandlers_enqueue_environment_variable_task", "relation": "calls", "context": "call", "confidence": "EXTRACTED", "source_file": "event_handlers.py", "source_location": "L244", "weight": 1.0}, {"source": "gptvli_event_handlers_eventhandlers_on_environment_variable_updated", "target": "gptvli_event_handlers_eventhandlers_get_environment_variable_changes", "relation": "calls", "context": "call", "confidence": "EXTRACTED", "source_file": "event_handlers.py", "source_location": "L252", "weight": 1.0}, {"source": "gptvli_event_handlers_eventhandlers_on_environment_variable_updated", "target": "gptvli_event_handlers_eventhandlers_enqueue_environment_variable_task", "relation": "calls", "context": "call", "confidence": "EXTRACTED", "source_file": "event_handlers.py", "source_location": "L257", "weight": 1.0}, {"source": "gptvli_event_handlers_eventhandlers_on_environment_variable_deleted", "target": "gptvli_event_handlers_eventhandlers_enqueue_environment_variable_task", "relation": "calls", "context": "call", "confidence": "EXTRACTED", "source_file": "event_handlers.py", "source_location": "L265", "weight": 1.0}, {"source": "gptvli_event_handlers_rationale_13", "target": "gptvli_event_handlers_eventhandlers", "relation": "rationale_for", "confidence": "EXTRACTED", "source_file": "event_handlers.py", "source_location": "L13", "weight": 1.0}, {"source": "gptvli_event_handlers_rationale_68", "target": "gptvli_event_handlers_eventhandlers_enqueue_environment_variable_task", "relation": "rationale_for", "confidence": "EXTRACTED", "source_file": "event_handlers.py", "source_location": "L68", "weight": 1.0}, {"source": "gptvli_event_handlers_rationale_108", "target": "gptvli_event_handlers_eventhandlers_enqueue_vector_sync_task", "relation": "rationale_for", "confidence": "EXTRACTED", "source_file": "event_handlers.py", "source_location": "L108", "weight": 1.0}, {"source": "gptvli_event_handlers_rationale_315", "target": "gptvli_event_handlers_eventhandlers_manual_trigger_matching", "relation": "rationale_for", "confidence": "EXTRACTED", "source_file": "event_handlers.py", "source_location": "L315", "weight": 1.0}], "raw_calls": [{"caller_nid": "gptvli_event_handlers_eventhandlers_init", "callee": "getLogger", "is_member_call": true, "source_file": "C:\\Users\\LifeCycle\\Desktop\\gptvli\\event_handlers.py", "source_location": "L19"}, {"caller_nid": "gptvli_event_handlers_eventhandlers_register_handlers", "callee": "listen", "is_member_call": true, "source_file": "C:\\Users\\LifeCycle\\Desktop\\gptvli\\event_handlers.py", "source_location": "L26"}, {"caller_nid": "gptvli_event_handlers_eventhandlers_register_handlers", "callee": "listen", "is_member_call": true, "source_file": "C:\\Users\\LifeCycle\\Desktop\\gptvli\\event_handlers.py", "source_location": "L27"}, {"caller_nid": "gptvli_event_handlers_eventhandlers_register_handlers", "callee": "listen", "is_member_call": true, "source_file": "C:\\Users\\LifeCycle\\Desktop\\gptvli\\event_handlers.py", "source_location": "L28"}, {"caller_nid": "gptvli_event_handlers_eventhandlers_register_handlers", "callee": "listen", "is_member_call": true, "source_file": "C:\\Users\\LifeCycle\\Desktop\\gptvli\\event_handlers.py", "source_location": "L29"}, {"caller_nid": "gptvli_event_handlers_eventhandlers_register_handlers", "callee": "listen", "is_member_call": true, "source_file": "C:\\Users\\LifeCycle\\Desktop\\gptvli\\event_handlers.py", "source_location": "L30"}, {"caller_nid": "gptvli_event_handlers_eventhandlers_register_handlers", "callee": "listen", "is_member_call": true, "source_file": "C:\\Users\\LifeCycle\\Desktop\\gptvli\\event_handlers.py", "source_location": "L31"}, {"caller_nid": "gptvli_event_handlers_eventhandlers_register_handlers", "callee": "listen", "is_member_call": true, "source_file": "C:\\Users\\LifeCycle\\Desktop\\gptvli\\event_handlers.py", "source_location": "L32"}, {"caller_nid": "gptvli_event_handlers_eventhandlers_register_handlers", "callee": "listen", "is_member_call": true, "source_file": "C:\\Users\\LifeCycle\\Desktop\\gptvli\\event_handlers.py", "source_location": "L33"}, {"caller_nid": "gptvli_event_handlers_eventhandlers_register_handlers", "callee": "listen", "is_member_call": true, "source_file": "C:\\Users\\LifeCycle\\Desktop\\gptvli\\event_handlers.py", "source_location": "L34"}, {"caller_nid": "gptvli_event_handlers_eventhandlers_register_handlers", "callee": "listen", "is_member_call": true, "source_file": "C:\\Users\\LifeCycle\\Desktop\\gptvli\\event_handlers.py", "source_location": "L35"}, {"caller_nid": "gptvli_event_handlers_eventhandlers_register_handlers", "callee": "info", "is_member_call": true, "source_file": "C:\\Users\\LifeCycle\\Desktop\\gptvli\\event_handlers.py", "source_location": "L38"}, {"caller_nid": "gptvli_event_handlers_eventhandlers_enqueue_rematch", "callee": "first", "is_member_call": true, "source_file": "C:\\Users\\LifeCycle\\Desktop\\gptvli\\event_handlers.py", "source_location": "L45"}, {"caller_nid": "gptvli_event_handlers_eventhandlers_enqueue_rematch", "callee": "execute", "is_member_call": true, "source_file": "C:\\Users\\LifeCycle\\Desktop\\gptvli\\event_handlers.py", "source_location": "L45"}, {"caller_nid": "gptvli_event_handlers_eventhandlers_enqueue_rematch", "callee": "where", "is_member_call": true, "source_file": "C:\\Users\\LifeCycle\\Desktop\\gptvli\\event_handlers.py", "source_location": "L46"}, {"caller_nid": "gptvli_event_handlers_eventhandlers_enqueue_rematch", "callee": "select", "is_member_call": false, "source_file": "C:\\Users\\LifeCycle\\Desktop\\gptvli\\event_handlers.py", "source_location": "L46"}, {"caller_nid": "gptvli_event_handlers_eventhandlers_enqueue_rematch", "callee": "in_", "is_member_call": true, "source_file": "C:\\Users\\LifeCycle\\Desktop\\gptvli\\event_handlers.py", "source_location": "L48"}, {"caller_nid": "gptvli_event_handlers_eventhandlers_enqueue_rematch", "callee": "execute", "is_member_call": true, "source_file": "C:\\Users\\LifeCycle\\Desktop\\gptvli\\event_handlers.py", "source_location": "L54"}, {"caller_nid": "gptvli_event_handlers_eventhandlers_enqueue_rematch", "callee": "values", "is_member_call": true, "source_file": "C:\\Users\\LifeCycle\\Desktop\\gptvli\\event_handlers.py", "source_location": "L55"}, {"caller_nid": "gptvli_event_handlers_eventhandlers_enqueue_rematch", "callee": "insert", "is_member_call": true, "source_file": "C:\\Users\\LifeCycle\\Desktop\\gptvli\\event_handlers.py", "source_location": "L55"}, {"caller_nid": "gptvli_event_handlers_eventhandlers_enqueue_rematch", "callee": "utcnow", "is_member_call": true, "source_file": "C:\\Users\\LifeCycle\\Desktop\\gptvli\\event_handlers.py", "source_location": "L62"}, {"caller_nid": "gptvli_event_handlers_eventhandlers_enqueue_rematch", "callee": "utcnow", "is_member_call": true, "source_file": "C:\\Users\\LifeCycle\\Desktop\\gptvli\\event_handlers.py", "source_location": "L63"}, {"caller_nid": "gptvli_event_handlers_eventhandlers_enqueue_environment_variable_task", "callee": "setdefault", "is_member_call": true, "source_file": "C:\\Users\\LifeCycle\\Desktop\\gptvli\\event_handlers.py", "source_location": "L75"}, {"caller_nid": "gptvli_event_handlers_eventhandlers_enqueue_environment_variable_task", "callee": "append", "is_member_call": true, "source_file": "C:\\Users\\LifeCycle\\Desktop\\gptvli\\event_handlers.py", "source_location": "L76"}, {"caller_nid": "gptvli_event_handlers_eventhandlers_dispatch_environment_variable_task", "callee": "delay", "is_member_call": true, "source_file": "C:\\Users\\LifeCycle\\Desktop\\gptvli\\event_handlers.py", "source_location": "L84"}, {"caller_nid": "gptvli_event_handlers_eventhandlers_dispatch_environment_variable_task", "callee": "warning", "is_member_call": true, "source_file": "C:\\Users\\LifeCycle\\Desktop\\gptvli\\event_handlers.py", "source_location": "L86"}, {"caller_nid": "gptvli_event_handlers_eventhandlers_dispatch_vector_sync_task", "callee": "delay", "is_member_call": true, "source_file": "C:\\Users\\LifeCycle\\Desktop\\gptvli\\event_handlers.py", "source_location": "L98"}, {"caller_nid": "gptvli_event_handlers_eventhandlers_dispatch_vector_sync_task", "callee": "warning", "is_member_call": true, "source_file": "C:\\Users\\LifeCycle\\Desktop\\gptvli\\event_handlers.py", "source_location": "L100"}, {"caller_nid": "gptvli_event_handlers_eventhandlers_enqueue_vector_sync_task", "callee": "object_session", "is_member_call": false, "source_file": "C:\\Users\\LifeCycle\\Desktop\\gptvli\\event_handlers.py", "source_location": "L113"}, {"caller_nid": "gptvli_event_handlers_eventhandlers_enqueue_vector_sync_task", "callee": "setdefault", "is_member_call": true, "source_file": "C:\\Users\\LifeCycle\\Desktop\\gptvli\\event_handlers.py", "source_location": "L116"}, {"caller_nid": "gptvli_event_handlers_eventhandlers_enqueue_vector_sync_task", "callee": "append", "is_member_call": true, "source_file": "C:\\Users\\LifeCycle\\Desktop\\gptvli\\event_handlers.py", "source_location": "L117"}, {"caller_nid": "gptvli_event_handlers_eventhandlers_on_session_after_commit", "callee": "pop", "is_member_call": true, "source_file": "C:\\Users\\LifeCycle\\Desktop\\gptvli\\event_handlers.py", "source_location": "L124"}, {"caller_nid": "gptvli_event_handlers_eventhandlers_on_session_after_commit", "callee": "items", "is_member_call": true, "source_file": "C:\\Users\\LifeCycle\\Desktop\\gptvli\\event_handlers.py", "source_location": "L131"}, {"caller_nid": "gptvli_event_handlers_eventhandlers_on_session_after_commit", "callee": "pop", "is_member_call": true, "source_file": "C:\\Users\\LifeCycle\\Desktop\\gptvli\\event_handlers.py", "source_location": "L135"}, {"caller_nid": "gptvli_event_handlers_eventhandlers_on_session_after_commit", "callee": "items", "is_member_call": true, "source_file": "C:\\Users\\LifeCycle\\Desktop\\gptvli\\event_handlers.py", "source_location": "L143"}, {"caller_nid": "gptvli_event_handlers_eventhandlers_on_session_after_rollback", "callee": "pop", "is_member_call": true, "source_file": "C:\\Users\\LifeCycle\\Desktop\\gptvli\\event_handlers.py", "source_location": "L147"}, {"caller_nid": "gptvli_event_handlers_eventhandlers_on_session_after_rollback", "callee": "pop", "is_member_call": true, "source_file": "C:\\Users\\LifeCycle\\Desktop\\gptvli\\event_handlers.py", "source_location": "L148"}, {"caller_nid": "gptvli_event_handlers_eventhandlers_on_property_created", "callee": "error", "is_member_call": true, "source_file": "C:\\Users\\LifeCycle\\Desktop\\gptvli\\event_handlers.py", "source_location": "L158"}, {"caller_nid": "gptvli_event_handlers_eventhandlers_on_property_updated", "callee": "intersection", "is_member_call": true, "source_file": "C:\\Users\\LifeCycle\\Desktop\\gptvli\\event_handlers.py", "source_location": "L179"}, {"caller_nid": "gptvli_event_handlers_eventhandlers_on_property_updated", "callee": "keys", "is_member_call": true, "source_file": "C:\\Users\\LifeCycle\\Desktop\\gptvli\\event_handlers.py", "source_location": "L179"}, {"caller_nid": "gptvli_event_handlers_eventhandlers_on_property_updated", "callee": "intersection", "is_member_call": true, "source_file": "C:\\Users\\LifeCycle\\Desktop\\gptvli\\event_handlers.py", "source_location": "L182"}, {"caller_nid": "gptvli_event_handlers_eventhandlers_on_property_updated", "callee": "keys", "is_member_call": true, "source_file": "C:\\Users\\LifeCycle\\Desktop\\gptvli\\event_handlers.py", "source_location": "L182"}, {"caller_nid": "gptvli_event_handlers_eventhandlers_on_property_updated", "callee": "error", "is_member_call": true, "source_file": "C:\\Users\\LifeCycle\\Desktop\\gptvli\\event_handlers.py", "source_location": "L185"}, {"caller_nid": "gptvli_event_handlers_eventhandlers_on_property_deleted", "callee": "error", "is_member_call": true, "source_file": "C:\\Users\\LifeCycle\\Desktop\\gptvli\\event_handlers.py", "source_location": "L191"}, {"caller_nid": "gptvli_event_handlers_eventhandlers_on_customer_created", "callee": "error", "is_member_call": true, "source_file": "C:\\Users\\LifeCycle\\Desktop\\gptvli\\event_handlers.py", "source_location": "L198"}, {"caller_nid": "gptvli_event_handlers_eventhandlers_on_customer_updated", "callee": "intersection", "is_member_call": true, "source_file": "C:\\Users\\LifeCycle\\Desktop\\gptvli\\event_handlers.py", "source_location": "L215"}, {"caller_nid": "gptvli_event_handlers_eventhandlers_on_customer_updated", "callee": "keys", "is_member_call": true, "source_file": "C:\\Users\\LifeCycle\\Desktop\\gptvli\\event_handlers.py", "source_location": "L215"}, {"caller_nid": "gptvli_event_handlers_eventhandlers_on_customer_updated", "callee": "error", "is_member_call": true, "source_file": "C:\\Users\\LifeCycle\\Desktop\\gptvli\\event_handlers.py", "source_location": "L218"}, {"caller_nid": "gptvli_event_handlers_eventhandlers_get_property_changes", "callee": "get", "is_member_call": true, "source_file": "C:\\Users\\LifeCycle\\Desktop\\gptvli\\event_handlers.py", "source_location": "L222"}, {"caller_nid": "gptvli_event_handlers_eventhandlers_get_property_changes", "callee": "keys", "is_member_call": true, "source_file": "C:\\Users\\LifeCycle\\Desktop\\gptvli\\event_handlers.py", "source_location": "L225"}, {"caller_nid": "gptvli_event_handlers_eventhandlers_get_property_changes", "callee": "items", "is_member_call": true, "source_file": "C:\\Users\\LifeCycle\\Desktop\\gptvli\\event_handlers.py", "source_location": "L226"}, {"caller_nid": "gptvli_event_handlers_eventhandlers_get_property_changes", "callee": "get", "is_member_call": true, "source_file": "C:\\Users\\LifeCycle\\Desktop\\gptvli\\event_handlers.py", "source_location": "L227"}, {"caller_nid": "gptvli_event_handlers_eventhandlers_get_property_changes", "callee": "get", "is_member_call": true, "source_file": "C:\\Users\\LifeCycle\\Desktop\\gptvli\\event_handlers.py", "source_location": "L228"}, {"caller_nid": "gptvli_event_handlers_eventhandlers_get_customer_changes", "callee": "get", "is_member_call": true, "source_file": "C:\\Users\\LifeCycle\\Desktop\\gptvli\\event_handlers.py", "source_location": "L233"}, {"caller_nid": "gptvli_event_handlers_eventhandlers_get_customer_changes", "callee": "keys", "is_member_call": true, "source_file": "C:\\Users\\LifeCycle\\Desktop\\gptvli\\event_handlers.py", "source_location": "L236"}, {"caller_nid": "gptvli_event_handlers_eventhandlers_get_customer_changes", "callee": "items", "is_member_call": true, "source_file": "C:\\Users\\LifeCycle\\Desktop\\gptvli\\event_handlers.py", "source_location": "L237"}, {"caller_nid": "gptvli_event_handlers_eventhandlers_get_customer_changes", "callee": "get", "is_member_call": true, "source_file": "C:\\Users\\LifeCycle\\Desktop\\gptvli\\event_handlers.py", "source_location": "L238"}, {"caller_nid": "gptvli_event_handlers_eventhandlers_get_customer_changes", "callee": "get", "is_member_call": true, "source_file": "C:\\Users\\LifeCycle\\Desktop\\gptvli\\event_handlers.py", "source_location": "L239"}, {"caller_nid": "gptvli_event_handlers_eventhandlers_on_environment_variable_created", "callee": "error", "is_member_call": true, "source_file": "C:\\Users\\LifeCycle\\Desktop\\gptvli\\event_handlers.py", "source_location": "L248"}, {"caller_nid": "gptvli_event_handlers_eventhandlers_on_environment_variable_updated", "callee": "error", "is_member_call": true, "source_file": "C:\\Users\\LifeCycle\\Desktop\\gptvli\\event_handlers.py", "source_location": "L261"}, {"caller_nid": "gptvli_event_handlers_eventhandlers_on_environment_variable_deleted", "callee": "error", "is_member_call": true, "source_file": "C:\\Users\\LifeCycle\\Desktop\\gptvli\\event_handlers.py", "source_location": "L269"}, {"caller_nid": "gptvli_event_handlers_eventhandlers_get_environment_variable_changes", "callee": "get", "is_member_call": true, "source_file": "C:\\Users\\LifeCycle\\Desktop\\gptvli\\event_handlers.py", "source_location": "L273"}, {"caller_nid": "gptvli_event_handlers_eventhandlers_get_environment_variable_changes", "callee": "keys", "is_member_call": true, "source_file": "C:\\Users\\LifeCycle\\Desktop\\gptvli\\event_handlers.py", "source_location": "L276"}, {"caller_nid": "gptvli_event_handlers_eventhandlers_get_environment_variable_changes", "callee": "items", "is_member_call": true, "source_file": "C:\\Users\\LifeCycle\\Desktop\\gptvli\\event_handlers.py", "source_location": "L277"}, {"caller_nid": "gptvli_event_handlers_eventhandlers_get_environment_variable_changes", "callee": "get", "is_member_call": true, "source_file": "C:\\Users\\LifeCycle\\Desktop\\gptvli\\event_handlers.py", "source_location": "L278"}, {"caller_nid": "gptvli_event_handlers_eventhandlers_get_environment_variable_changes", "callee": "get", "is_member_call": true, "source_file": "C:\\Users\\LifeCycle\\Desktop\\gptvli\\event_handlers.py", "source_location": "L279"}, {"caller_nid": "gptvli_event_handlers_eventhandlers_on_session_after_commit", "callee": "pop", "is_member_call": true, "source_file": "C:\\Users\\LifeCycle\\Desktop\\gptvli\\event_handlers.py", "source_location": "L284"}, {"caller_nid": "gptvli_event_handlers_eventhandlers_on_session_after_commit", "callee": "items", "is_member_call": true, "source_file": "C:\\Users\\LifeCycle\\Desktop\\gptvli\\event_handlers.py", "source_location": "L291"}, {"caller_nid": "gptvli_event_handlers_eventhandlers_on_session_after_commit", "callee": "pop", "is_member_call": true, "source_file": "C:\\Users\\LifeCycle\\Desktop\\gptvli\\event_handlers.py", "source_location": "L295"}, {"caller_nid": "gptvli_event_handlers_eventhandlers_on_session_after_commit", "callee": "items", "is_member_call": true, "source_file": "C:\\Users\\LifeCycle\\Desktop\\gptvli\\event_handlers.py", "source_location": "L303"}, {"caller_nid": "gptvli_event_handlers_eventhandlers_on_session_after_rollback", "callee": "pop", "is_member_call": true, "source_file": "C:\\Users\\LifeCycle\\Desktop\\gptvli\\event_handlers.py", "source_location": "L307"}, {"caller_nid": "gptvli_event_handlers_eventhandlers_on_session_after_rollback", "callee": "pop", "is_member_call": true, "source_file": "C:\\Users\\LifeCycle\\Desktop\\gptvli\\event_handlers.py", "source_location": "L308"}, {"caller_nid": "gptvli_event_handlers_eventhandlers_manual_trigger_matching", "callee": "begin", "is_member_call": true, "source_file": "C:\\Users\\LifeCycle\\Desktop\\gptvli\\event_handlers.py", "source_location": "L316"}, {"caller_nid": "gptvli_event_handlers_eventhandlers_manual_trigger_matching", "callee": "first", "is_member_call": true, "source_file": "C:\\Users\\LifeCycle\\Desktop\\gptvli\\event_handlers.py", "source_location": "L320"}, {"caller_nid": "gptvli_event_handlers_eventhandlers_manual_trigger_matching", "callee": "in_", "is_member_call": true, "source_file": "C:\\Users\\LifeCycle\\Desktop\\gptvli\\event_handlers.py", "source_location": "L322"}, {"caller_nid": "gptvli_event_handlers_eventhandlers_manual_trigger_matching", "callee": "add", "is_member_call": true, "source_file": "C:\\Users\\LifeCycle\\Desktop\\gptvli\\event_handlers.py", "source_location": "L325"}, {"caller_nid": "gptvli_event_handlers_eventhandlers_manual_trigger_matching", "callee": "RematchQueue", "is_member_call": false, "source_file": "C:\\Users\\LifeCycle\\Desktop\\gptvli\\event_handlers.py", "source_location": "L326"}, {"caller_nid": "gptvli_event_handlers_eventhandlers_manual_trigger_matching", "callee": "first", "is_member_call": true, "source_file": "C:\\Users\\LifeCycle\\Desktop\\gptvli\\event_handlers.py", "source_location": "L337"}, {"caller_nid": "gptvli_event_handlers_eventhandlers_manual_trigger_matching", "callee": "in_", "is_member_call": true, "source_file": "C:\\Users\\LifeCycle\\Desktop\\gptvli\\event_handlers.py", "source_location": "L339"}, {"caller_nid": "gptvli_event_handlers_eventhandlers_manual_trigger_matching", "callee": "add", "is_member_call": true, "source_file": "C:\\Users\\LifeCycle\\Desktop\\gptvli\\event_handlers.py", "source_location": "L342"}, {"caller_nid": "gptvli_event_handlers_eventhandlers_manual_trigger_matching", "callee": "RematchQueue", "is_member_call": false, "source_file": "C:\\Users\\LifeCycle\\Desktop\\gptvli\\event_handlers.py", "source_location": "L343"}, {"caller_nid": "gptvli_event_handlers_eventhandlers_manual_trigger_matching", "callee": "strftime", "is_member_call": true, "source_file": "C:\\Users\\LifeCycle\\Desktop\\gptvli\\event_handlers.py", "source_location": "L351"}, {"caller_nid": "gptvli_event_handlers_eventhandlers_manual_trigger_matching", "callee": "utcnow", "is_member_call": true, "source_file": "C:\\Users\\LifeCycle\\Desktop\\gptvli\\event_handlers.py", "source_location": "L351"}, {"caller_nid": "gptvli_event_handlers_eventhandlers_get_matching_stats", "callee": "replace", "is_member_call": true, "source_file": "C:\\Users\\LifeCycle\\Desktop\\gptvli\\event_handlers.py", "source_location": "L355"}, {"caller_nid": "gptvli_event_handlers_eventhandlers_get_matching_stats", "callee": "utcnow", "is_member_call": true, "source_file": "C:\\Users\\LifeCycle\\Desktop\\gptvli\\event_handlers.py", "source_location": "L355"}, {"caller_nid": "gptvli_event_handlers_eventhandlers_get_matching_stats", "callee": "count", "is_member_call": true, "source_file": "C:\\Users\\LifeCycle\\Desktop\\gptvli\\event_handlers.py", "source_location": "L356"}, {"caller_nid": "gptvli_event_handlers_eventhandlers_get_matching_stats", "callee": "query", "is_member_call": true, "source_file": "C:\\Users\\LifeCycle\\Desktop\\gptvli\\event_handlers.py", "source_location": "L356"}, {"caller_nid": "gptvli_event_handlers_eventhandlers_get_matching_stats", "callee": "count", "is_member_call": true, "source_file": "C:\\Users\\LifeCycle\\Desktop\\gptvli\\event_handlers.py", "source_location": "L357"}, {"caller_nid": "gptvli_event_handlers_eventhandlers_get_matching_stats", "callee": "query", "is_member_call": true, "source_file": "C:\\Users\\LifeCycle\\Desktop\\gptvli\\event_handlers.py", "source_location": "L357"}, {"caller_nid": "gptvli_event_handlers_eventhandlers_get_matching_stats", "callee": "count", "is_member_call": true, "source_file": "C:\\Users\\LifeCycle\\Desktop\\gptvli\\event_handlers.py", "source_location": "L358"}, {"caller_nid": "gptvli_event_handlers_eventhandlers_get_matching_stats", "callee": "query", "is_member_call": true, "source_file": "C:\\Users\\LifeCycle\\Desktop\\gptvli\\event_handlers.py", "source_location": "L358"}, {"caller_nid": "gptvli_event_handlers_eventhandlers_get_matching_stats", "callee": "count", "is_member_call": true, "source_file": "C:\\Users\\LifeCycle\\Desktop\\gptvli\\event_handlers.py", "source_location": "L362"}, {"caller_nid": "gptvli_event_handlers_eventhandlers_get_matching_stats", "callee": "query", "is_member_call": true, "source_file": "C:\\Users\\LifeCycle\\Desktop\\gptvli\\event_handlers.py", "source_location": "L362"}, {"caller_nid": "gptvli_event_handlers_eventhandlers_get_matching_stats", "callee": "count", "is_member_call": true, "source_file": "C:\\Users\\LifeCycle\\Desktop\\gptvli\\event_handlers.py", "source_location": "L363"}, {"caller_nid": "gptvli_event_handlers_eventhandlers_get_matching_stats", "callee": "query", "is_member_call": true, "source_file": "C:\\Users\\LifeCycle\\Desktop\\gptvli\\event_handlers.py", "source_location": "L363"}, {"caller_nid": "gptvli_event_handlers_eventhandlers_get_matching_stats", "callee": "isoformat", "is_member_call": true, "source_file": "C:\\Users\\LifeCycle\\Desktop\\gptvli\\event_handlers.py", "source_location": "L371"}, {"caller_nid": "gptvli_event_handlers_eventhandlers_get_matching_stats", "callee": "utcnow", "is_member_call": true, "source_file": "C:\\Users\\LifeCycle\\Desktop\\gptvli\\event_handlers.py", "source_location": "L371"}, {"caller_nid": "gptvli_event_handlers_eventhandlers_get_matching_stats", "callee": "error", "is_member_call": true, "source_file": "C:\\Users\\LifeCycle\\Desktop\\gptvli\\event_handlers.py", "source_location": "L374"}, {"caller_nid": "gptvli_event_handlers_eventhandlers_get_matching_stats", "callee": "isoformat", "is_member_call": true, "source_file": "C:\\Users\\LifeCycle\\Desktop\\gptvli\\event_handlers.py", "source_location": "L375"}, {"caller_nid": "gptvli_event_handlers_eventhandlers_get_matching_stats", "callee": "utcnow", "is_member_call": true, "source_file": "C:\\Users\\LifeCycle\\Desktop\\gptvli\\event_handlers.py", "source_location": "L375"}]}